{
    "status": {
        "a_6": {
            "yes": 1536,
            "no": 0,
            "undecided": 1024,
            "unknown": 1536,
            "pyes": 0.7686733563227337,
            "pno": 0.0,
            "pundecided": 0.1405065234292668,
            "punknown": 0.09082012024800015,
            "time": 164.8360071182251,
            "delp_calls": 2810,
            "percY": 384439372.8,
            "percN": 0.0,
            "percU": 256292915.2,
            "percUNK": 384439372.8,
            "l": 0.7686733563227337,
            "u": 1.0,
            "flag": "INTEREST"
        },
        "a_9": {
            "yes": 1716,
            "no": 640,
            "undecided": 1716,
            "unknown": 24,
            "pyes": 0.8369231940325272,
            "pno": 0.009263625506822864,
            "pundecided": 0.1538130991650452,
            "punknown": 8.129560386295079e-08,
            "time": 164.361718416214,
            "delp_calls": 2810,
            "percY": 429490861.8,
            "percN": 160183072.0,
            "percU": 429490861.8,
            "percUNK": 6006865.2,
            "l": 0.8369231940325272,
            "u": 0.9907363744931771,
            "flag": "INTEREST"
        }
    },
    "data": {
        "n_samples": 25028605,
        "time": 600.0000112056732,
        "repeated_worlds": 25020413,
        "repeated_progs": 25022985,
        "unique_progs": 5620,
        "delp_calls": 5620
    }
}