{
    "status": {
        "d_42": {
            "yes": 1163,
            "no": 0,
            "undecided": 145,
            "unknown": 26,
            "pyes": 0.0746330912971621,
            "pno": 0.0,
            "pundecided": 0.020672092471849514,
            "punknown": 0.0006681982047117263,
            "time": 52.423118352890015,
            "delp_calls": 1334,
            "percY": 30714.83,
            "percN": 0.0,
            "percU": 3829.45,
            "percUNK": 686.66,
            "l": 0.0746330912971621,
            "u": 1.0
        },
        "a_15": {
            "yes": 244,
            "no": 82,
            "undecided": 980,
            "unknown": 1,
            "pyes": 0.07144578229476777,
            "pno": 5.143115556841196e-05,
            "pundecided": 0.14666962076475454,
            "punknown": 1.9022141647872002e-05,
            "time": 58.67929124832153,
            "delp_calls": 1307,
            "percY": 6444.04,
            "percN": 2165.62,
            "percU": 25881.8,
            "percUNK": 26.41,
            "l": 0.07144578229476777,
            "u": 0.9999485688444316
        }
    },
    "data": {
        "n_samples": 2641,
        "time": 600.2686865329742,
        "repeated_programs": 0,
        "inconsistent_programs": 0,
        "worlds_consulted": 2252,
        "delp_calls": 2641
    }
}