{
    "status": {
        "~d_17": {
            "yes": 621548,
            "no": 0,
            "undecided": 0,
            "unknown": 0,
            "pyes": 0.03562301223491267,
            "pno": 0.0,
            "pundecided": 0.0,
            "punknown": 0.0,
            "time": 27167.05629658699,
            "delp_calls": 160,
            "percY": 11686072014.88,
            "percN": 0.0,
            "percU": 0.0,
            "percUNK": 0.0,
            "l": 0.03562301223491267,
            "u": 1.0
        },
        "~a_5": {
            "yes": 597163,
            "no": 0,
            "undecided": 0,
            "unknown": 0,
            "pyes": 0.03567154722619967,
            "pno": 0.0,
            "pundecided": 0.0,
            "punknown": 0.0,
            "time": 32083.90024971962,
            "delp_calls": 160,
            "percY": 11227595974.28,
            "percN": 0.0,
            "percU": 0.0,
            "percUNK": 0.0,
            "l": 0.03567154722619967,
            "u": 1.0
        },
        "~a_7": {
            "yes": 29283,
            "no": 441196,
            "undecided": 156566,
            "unknown": 0,
            "pyes": 0.0038491673302448585,
            "pno": 0.023483379147851636,
            "pundecided": 0.009881738164761806,
            "punknown": 0.0,
            "time": 42236.32670593262,
            "delp_calls": 160,
            "percY": 550566081.48,
            "percN": 8295173065.76,
            "percU": 2943685042.96,
            "percUNK": 0.0,
            "l": 0.0038491673302448585,
            "u": 0.9765166208521484
        }
    },
    "data": {
        "n_samples": 1880156,
        "time": 900.0009620189667,
        "repeated_worlds": 34400,
        "repeated_progs": 1879676,
        "unique_progs": 480,
        "delp_calls": 480
    }
}