{
    "status": {
        "a_7": {
            "yes": 2221,
            "no": 192,
            "undecided": 1524,
            "unknown": 45,
            "pyes": 0.7836933073686635,
            "pno": 0.00026079809533723005,
            "pundecided": 0.05683090406530391,
            "punknown": 3.6222097704109356e-05,
            "time": 158.76636934280396,
            "delp_calls": 3982,
            "percY": 88440.22,
            "percN": 7645.44,
            "percU": 60685.68,
            "percUNK": 1791.9,
            "l": 0.7836933073686635,
            "u": 0.9997392019046628,
            "flag": "INTEREST"
        }
    },
    "data": {
        "n_samples": 3982,
        "time": 300.0344569683075,
        "repeated_programs": 0,
        "inconsistent_programs": 0,
        "worlds_consulted": 3455,
        "delp_calls": 3982
    }
}