{
    "status": {
        "a_6": {
            "yes": 252926,
            "no": 0,
            "undecided": 253048,
            "unknown": 0,
            "pyes": 0.0213417109387775,
            "pno": 0.0,
            "pundecided": 0.007563483750080106,
            "punknown": 0.0,
            "time": 21068.73077392578,
            "delp_calls": 2048,
            "percY": 2481677031.62,
            "percN": 0.0,
            "percU": 2482874079.76,
            "percUNK": 0.0,
            "l": 0.0213417109387775,
            "u": 1.0
        },
        "a_8": {
            "yes": 114800,
            "no": 115762,
            "undecided": 230644,
            "unknown": 0,
            "pyes": 0.016586530691150243,
            "pno": 0.003692473452631704,
            "pundecided": 0.007776531372151098,
            "punknown": 0.0,
            "time": 23142.6920273304,
            "delp_calls": 2048,
            "percY": 1126402676.0,
            "percN": 1135841694.94,
            "percU": 2263048944.28,
            "percUNK": 0.0,
            "l": 0.016586530691150243,
            "u": 0.9963075265473683
        }
    },
    "data": {
        "n_samples": 981187,
        "time": 600.0004179477692,
        "repeated_worlds": 14007,
        "repeated_progs": 977091,
        "unique_progs": 4096,
        "delp_calls": 4096
    }
}