{
    "status": {
        "a_1": {
            "yes": 1878,
            "no": 0,
            "undecided": 0,
            "unknown": 1431,
            "pyes": 0.02794076452422771,
            "pno": 0.0,
            "pundecided": 0.0,
            "punknown": 0.00028671882079162964,
            "time": 139.51730155944824,
            "delp_calls": 3309,
            "percY": 62143.02,
            "percN": 0.0,
            "percU": 0.0,
            "percUNK": 47351.79,
            "l": 0.02794076452422771,
            "u": 1.0
        }
    },
    "data": {
        "n_samples": 3309,
        "time": 300.0827021598816,
        "repeated_programs": 0,
        "inconsistent_programs": 0,
        "worlds_consulted": 16526,
        "delp_calls": 3309
    }
}