{
    "status": {
        "a_0": {
            "yes": 4960,
            "no": 0,
            "undecided": 0,
            "unknown": 0,
            "pyes": 1.0000000000000002,
            "pno": 0.0,
            "pundecided": 0.0,
            "punknown": 0.0,
            "time": 232.65318274497986,
            "delp_calls": 4960,
            "percY": 741024.0,
            "percN": 0.0,
            "percU": 0.0,
            "percUNK": 0.0,
            "l": 1.0000000000000002,
            "u": 1.0,
            "flag": "INTEREST"
        },
        "a_6": {
            "yes": 4127,
            "no": 0,
            "undecided": 874,
            "unknown": 0,
            "pyes": 0.6536584132814982,
            "pno": 0.0,
            "pundecided": 0.34634158671850196,
            "punknown": 0.0,
            "time": 232.96861004829407,
            "delp_calls": 5001,
            "percY": 616573.8,
            "percN": 0.0,
            "percU": 130575.6,
            "percUNK": 0.0,
            "l": 0.6536584132814982,
            "u": 1.0,
            "flag": "INTEREST"
        },
        "a_8": {
            "yes": 865,
            "no": 2873,
            "undecided": 1241,
            "unknown": 0,
            "pyes": 0.03243702880993248,
            "pno": 0.5926219958746742,
            "pundecided": 0.37494097531539416,
            "punknown": 0.0,
            "time": 234.04188561439514,
            "delp_calls": 4979,
            "percY": 129231.0,
            "percN": 429226.2,
            "percU": 185405.4,
            "percUNK": 0.0,
            "l": 0.03243702880993248,
            "u": 0.40737800412532577,
            "flag": "INTEREST"
        }
    },
    "data": {
        "n_samples": 14940,
        "time": 900.1153643131256,
        "repeated_programs": 0,
        "inconsistent_programs": 0,
        "worlds_consulted": 12288,
        "delp_calls": 14940
    }
}