{
    "status": {
        "a_7": {
            "yes": 1172,
            "no": 386,
            "undecided": 1428,
            "unknown": 0,
            "pyes": 0.18762268800848597,
            "pno": 0.017770748438712364,
            "pundecided": 0.20407281379192282,
            "punknown": 0.0,
            "time": 136.85279273986816,
            "delp_calls": 5679,
            "percY": 132318.8,
            "percN": 43579.4,
            "percU": 161221.2,
            "percUNK": 0.0,
            "l": 0.18762268800848597,
            "u": 0.9822292515612876
        },
        "~a_8": {
            "yes": 977,
            "no": 508,
            "undecided": 1563,
            "unknown": 1,
            "pyes": 0.08596412770568775,
            "pno": 0.12480698463743387,
            "pundecided": 0.22225527613735874,
            "punknown": 0.00010638609912197864,
            "time": 141.271071434021,
            "delp_calls": 5611,
            "percY": 110303.3,
            "percN": 57353.2,
            "percU": 176462.7,
            "percUNK": 112.9,
            "l": 0.08596412770568775,
            "u": 0.8751930153625661
        }
    },
    "data": {
        "n_samples": 11290,
        "time": 600.0296773910522,
        "repeated_programs": 0,
        "inconsistent_programs": 5255,
        "worlds_consulted": 3114,
        "delp_calls": 11290
    }
}