{
    "status": {
        "~d_11": {
            "yes": 2048,
            "no": 0,
            "undecided": 2048,
            "unknown": 0,
            "pyes": 0.9699999999999989,
            "pno": 0.0,
            "pundecided": 0.03000000000000001,
            "punknown": 0.0,
            "time": 225.96141052246094,
            "delp_calls": 64,
            "percY": 335564779.52,
            "percN": 0.0,
            "percU": 335564779.52,
            "percUNK": 0.0,
            "l": 0.9699999999999989,
            "u": 1.0,
            "flag": "INTEREST"
        }
    },
    "data": {
        "n_samples": 16384999,
        "time": 300.00001764297485,
        "repeated_worlds": 16380903,
        "repeated_progs": 16384935,
        "unique_progs": 64,
        "delp_calls": 64
    }
}